{
  "id": "db-sqlite-intro-001",
  "title": "SQLite Shell Basics",
  "difficulty": "Easy",
  "category": "Databases",
  "bundled": true,
  "estimatedTimeMinutes": 25,
  "description": "Practice SELECT queries in an isolated Docker training environment. Complete the briefing tasks and create the completion marker.",
  "labMode": "target-only",
  "runtime": "docker",
  "docker": {
    "image": "sysadmin-game/db-sqlite-intro-001:latest",
    "buildPath": "..",
    "ports": []
  },
  "tags": [
    "databases",
    "select",
    "bundled"
  ],
  "safetyNotes": [
    "Commands run only inside the lab container — not on your host.",
    "Do not paste destructive commands (rm -rf /, mkfs, dd to disks) even inside the lab."
  ],
  "tasks": [
    "Open the lab terminal (session user is already logged in)",
    "Read the briefing in ~/README.txt about SELECT queries",
    "Create the read marker: touch /tmp/db-sqlite-intro-001-read",
    "Create the completion marker: touch /tmp/db-sqlite-intro-001-complete",
    "Use Check in the lab panel — the lab completes when objectives pass"
  ],
  "objectivesPublic": [
    {
      "id": "read-briefing",
      "label": "Read the briefing",
      "text": "Read ~/README.txt and mark it read.",
      "hint": "Run: touch /tmp/db-sqlite-intro-001-read"
    },
    {
      "id": "complete-lab",
      "label": "Finish the exercise",
      "text": "Apply what you learned about SELECT queries and create the completion marker.",
      "hint": "Run: touch /tmp/db-sqlite-intro-001-complete"
    }
  ],
  "objectives": [
    {
      "id": "read-briefing",
      "autoCheck": "fileExists",
      "path": "/tmp/db-sqlite-intro-001-read"
    },
    {
      "id": "complete-lab",
      "autoCheck": "fileExists",
      "path": "/tmp/db-sqlite-intro-001-complete"
    }
  ],
  "hints": [
    "Focus on SELECT queries.",
    "Use ls, cat, and touch — no root privileges required.",
    "Completion marker path: /tmp/db-sqlite-intro-001-complete"
  ],
  "successCriteria": [
    "Briefing read marker exists at /tmp/db-sqlite-intro-001-read",
    "Completion marker exists at /tmp/db-sqlite-intro-001-complete"
  ],
  "validation": {
    "type": "fileExists",
    "path": "/tmp/db-sqlite-intro-001-complete"
  },
  "postLabReview": {
    "summary": "You practiced SELECT queries in a safe container.",
    "skillsPracticed": [
      "SQLite Shell Basics reinforces everyday sysadmin skills.",
      "Always verify files with ls -l after creating markers.",
      "Repeat the lab to build muscle memory."
    ]
  },
  "xpReward": 50,
  "unlockRequirements": {
    "minLevel": 4,
    "requiredLabs": [
      "shell-basics-001"
    ]
  }
}
